mistool/__init__.py
mistool/datetime_use.py
mistool/latex_use.py
mistool/os_use.py
mistool/python_use.py
mistool/string_use.py
mistool/term_use.py
mistool/url_use.py
mistool/config/__init__.py
mistool/config/ascii.py
mistool/config/date_name.py
mistool/config/frame.py
mistool/config/latex.py
mistool/config/pattern.py
mistool-1.2.6b0.dist-info/METADATA
mistool-1.2.6b0.dist-info/WHEEL
mistool-1.2.6b0.dist-info/top_level.txt
mistool-1.2.6b0.dist-info/RECORD
